jpfmanager
