Metadata-Version: 2.1
Name: jpfmanager
Version: 0.0.3
Summary: File manager to deal with json and pickle files
Home-page: https://github.com/IbrahimABBAS85/jpf
Author: Ibrahim Abbas
Author-email: i.abbas85@gmail.com
License: UNKNOWN
Platform: UNKNOWN
Classifier: Programming Language :: Python :: 3
Classifier: License :: OSI Approved :: MIT License
Classifier: Operating System :: OS Independent
Requires-Python: >=3.6
